README.md
setup.py
taorunner/__init__.py
taorunner/main.py
taorunner/runner_utils.py
taorunner/tao_runner.py
taorunner.egg-info/PKG-INFO
taorunner.egg-info/SOURCES.txt
taorunner.egg-info/dependency_links.txt
taorunner.egg-info/entry_points.txt
taorunner.egg-info/top_level.txt